fold/__init__.py
fold/__main__.py
math_fold-0.1.5.dist-info/METADATA
math_fold-0.1.5.dist-info/RECORD
math_fold-0.1.5.dist-info/WHEEL
math_fold-0.1.5.dist-info/entry_points.txt
math_fold-0.1.5.dist-info/top_level.txt
