Metadata-Version: 2.1
Name: math-fold
Version: 0.1.5
Summary: back math notaion in CLI
Home-page: https://github.com/weaming/math-fold
Author: weaming
Author-email: garden.yuen@gmail.com
License: UNKNOWN
Project-URL: Source, https://github.com/weaming/math-fold
Project-URL: Bug Reports, https://github.com/weaming/math-fold
Keywords: math
Platform: UNKNOWN
